meeg_tools/__init__.py
meeg_tools/analysis_pipeline.py
meeg_tools/connectivity.py
meeg_tools/preprocessing.py
meeg_tools/time_frequency.py
meeg_tools/tests/__init__.py
meeg_tools/tests/test_preprocessing.py
meeg_tools/tests/test_utils_epochs.py
meeg_tools/tests/test_utils_raw.py
meeg_tools/utils/__init__.py
meeg_tools/utils/config.py
meeg_tools/utils/epochs.py
meeg_tools/utils/log.py
meeg_tools/utils/raw.py
meeg_tools-0.3.6.dist-info/LICENSE
meeg_tools-0.3.6.dist-info/METADATA
meeg_tools-0.3.6.dist-info/WHEEL
meeg_tools-0.3.6.dist-info/top_level.txt
meeg_tools-0.3.6.dist-info/RECORD
