Metadata-Version: 2.1
Name: meeg-tools
Version: 0.3.6
Summary: EEG/MEEG data preprocessing and analyses tools
Home-page: https://github.com/weiglszonja/meeg-tools
Author: Szonja Weigl
Author-email: weigl.anna.szonja@gmail.com
License: UNKNOWN
Platform: UNKNOWN
Requires-Python: <3.10.1
License-File: LICENSE
Requires-Dist: mne
Requires-Dist: python-picard
Requires-Dist: PyQt5
Requires-Dist: scipy
Requires-Dist: pandas
Requires-Dist: autoreject
Requires-Dist: pyprep
Requires-Dist: jupyter
Requires-Dist: joblib
Requires-Dist: sklearn
Requires-Dist: matplotlib
Requires-Dist: ipyfilechooser
Requires-Dist: h5py
Requires-Dist: tqdm
Requires-Dist: pyyaml (~=6.0)
Requires-Dist: yasa
Requires-Dist: mne-connectivity
Requires-Dist: h5netcdf
